paddle_prompt/__init__.py
paddle_prompt/config.py
paddle_prompt/data_reader.py
paddle_prompt/joint_loss.py
paddle_prompt/predictor.py
paddle_prompt/schema.py
paddle_prompt/trainer.py
paddle_prompt/utils.py
paddle_prompt/version.py
paddle_prompt/losses/__init__.py
paddle_prompt/models/__init__.py
paddle_prompt/models/classification.py
paddle_prompt/models/prompt.py
paddle_prompt/models/utils.py
paddle_prompt/plms/__init__.py
paddle_prompt/plms/ernie.py
paddle_prompt/processors/__init__.py
paddle_prompt/processors/base_processor.py
paddle_prompt/processors/tnews.py
paddle_prompt/templates/__init__.py
paddle_prompt/templates/base_template.py
paddle_prompt/templates/engine.py
paddle_prompt/templates/manual_template.py
paddle_prompt/verbalizers/__init__.py
paddle_prompt/verbalizers/base_verbalizer.py
paddle_prompt/verbalizers/manual_verbalizer.py
paddle_prompt-0.0.5.dist-info/LICENSE
paddle_prompt-0.0.5.dist-info/METADATA
paddle_prompt-0.0.5.dist-info/WHEEL
paddle_prompt-0.0.5.dist-info/top_level.txt
paddle_prompt-0.0.5.dist-info/RECORD
