Metadata-Version: 2.1
Name: paddle-prompt
Version: 0.0.5
Summary: Prompt Toolkit for PaddlePaddle Deep Learning Framework
Home-page: https://github.com/wj-Mcat/paddle-prompt
Author: wj-Mcat (吴京京)
Author-email: wjmcater@gmail.com
License: Apache-2.0
Platform: UNKNOWN
Classifier: Programming Language :: Python :: 3.7
Classifier: Programming Language :: Python :: 3.8
Classifier: Programming Language :: Python :: 3.9
Classifier: License :: OSI Approved :: Apache Software License
Classifier: Operating System :: OS Independent
Requires-Dist: semver
Requires-Dist: typed-argument-parser
Requires-Dist: numpy
Requires-Dist: dataclasses-json
Requires-Dist: paddlenlp
